botfleet/__init__.py
botfleet/_client.py
botfleet/errors.py
botfleet/pagination.py
botfleet/types.py
botfleet/resources/__init__.py
botfleet/resources/_base.py
botfleet/resources/bot.py
botfleet/resources/bot_builder_job.py
botfleet/resources/bot_executor_cron_jobs.py
botfleet/resources/bot_executor_job.py
botfleet/resources/bot_template.py
botfleet/resources/build.py
botfleet/resources/execution.py
botfleet/resources/store.py
botfleet-0.1.0.dist-info/LICENSE
botfleet-0.1.0.dist-info/METADATA
botfleet-0.1.0.dist-info/WHEEL
botfleet-0.1.0.dist-info/top_level.txt
botfleet-0.1.0.dist-info/RECORD
